Workbook

Sheet Cover Page
C4: 3 Statement Model
C8: Get 10% OFF our course using coupon code EMAIL10
C10: Get Our Excel for Business & Finance Course
C14: Made by Kenji Explains
C16: Note
C17: This 3 statement Excel model is solely for educational purposes and should not be used for any other purpose.
C18: All content is copyright material of Kenji Explains.
C19: This Excel model may not be reproduced or distributed by any means, including printing, screencapturing, or any other method without the prior permission of the publisher.

Sheet Income Statement
B2: Income Statement
B3: $ in actual figures | C3: 44562 | D3: =EDATE(C3,12) -> 44927 | E3: =EDATE(D3,12) -> 45292 | F3: =EDATE(E3,12) -> 45658 | G3: =EDATE(F3,12) -> 46023
B4: Revenue
B5: Gross Revenue | C5: =C32*C33 -> 25000 | D5: =D32*D33 -> 2500 | E5: =E32*E33 -> 32500 | F5: =F32*F33 -> 40000 | G5: =G32*G33 -> 50000
B6: Discounts | C6: =C5* - C34 -> -1250 | D6: =D5* - D34 -> -125 | E6: =E5* - E34 -> -1625 | F6: =F5* - F34 -> -2000 | G6: =G5* - G34 -> -2500
B7: Net Revenue | C7: =SUM(C5:C6) -> 23750 | D7: =SUM(D5:D6) -> 2375 | E7: =SUM(E5:E6) -> 30875 | F7: =SUM(F5:F6) -> 38000 | G7: =SUM(G5:G6) -> 47500
B8: Cost of Goods Sold (COGS)
B9: Raw Materials | C9: =-C5*C37 -> -7500 | D9: =-D5*D37 -> -750 | E9: =-E5*E37 -> -9750 | F9: =-F5*F37 -> -12000 | G9: =-G5*G37 -> -15000
B10: Fulfillment | C10: =-C5*C38 -> -1750 | D10: =-D5*D38 -> -175 | E10: =-E5*E38 -> -2275 | F10: =-F5*F38 -> -2800 | G10: =-G5*G38 -> -3500
B11: Transaction Fees | C11: =-C5*C39 -> -500 | D11: =-D5*D39 -> -50 | E11: =-E5*E39 -> -650 | F11: =-F5*F39 -> -800 | G11: =-G5*G39 -> -1000
B12: Total COGS | C12: =SUM(C9:C11) -> -9750 | D12: -9657 | E12: =SUM(E9:E11) -> -12675 | F12: =SUM(F9:F11) -> -15600 | G12: =SUM(G9:G11) -> -19500
B13: Gross Profit | C13: =C7+C12 -> 14000 | D13: =D7-D12 -> 12032 | E13: =E7+E12 -> 18200 | F13: =F7+F12 -> 22400 | G13: =G7+G12 -> 28000
B14: Gross Profit Margin % | C14: =C13/C7 -> 0.58947368 | D14: =D13/D7 -> 5.0661053 | E14: =E13/E7 -> 0.58947368 | F14: =F13/F7 -> 0.58947368 | G14: =G13/G7 -> 0.58947368
B15: Operating Expenses
B16: Labor | C16: =-C5*C42 -> -3750 | D16: =-D5*D42 -> -375 | E16: =-E5*E42 -> -4875 | F16: =-F5*F42 -> -6000 | G16: =-G5*G42 -> -7500
B17: Marketing | C17: =-C5*C43 -> -1250 | D17: =-D5*D43 -> -125 | E17: =-E5*E43 -> -1625 | F17: =-F5*F43 -> -2000 | G17: =-G5*G43 -> -2500
B18: SGA & Other | C18: =-C5*C44 -> -1250 | D18: =-D5*D44 -> -125 | E18: =-E5*E44 -> -1625 | F18: =-F5*F44 -> -2000 | G18: =-G5*G44 -> -2500
B19: Total OpEx | C19: =C16+C17+C18 -> -6250 | D19: =D16+D17+D18 -> -625 | E19: =E16+E17+E18 -> -8125 | F19: =F16+F17+F18 -> -10000 | G19: =G16+G17+G18 -> -12500
B20: EBITDA | C20: =C13+C19 -> 7750 | D20: =D13+D19 -> 11407 | E20: =E13+E19 -> 10075 | F20: =F13+F19 -> 12400 | G20: =G13+G19 -> 15500
B21: Depreciation & Amortization | C21: =-'Fixed Assets'!D15 -> 500 | D21: =-'Fixed Assets'!E15 -> 750 | E21: =-'Fixed Assets'!F15 -> 750 | F21: =-'Fixed Assets'!G15 -> 750 | G21: =-'Fixed Assets'!H15 -> -3
B22: EBIT | C22: =SUM(C20,C21) -> 8250 | D22: =SUM(D20,D21) -> 12157 | E22: =SUM(E20,E21) -> 10825 | F22: =SUM(F20,F21) -> 13150 | G22: =SUM(G20,G21) -> 15497
B23: Interest Expense | C23: =-'Balance Sheet'!D42 -> -665 | D23: =-'Balance Sheet'!E42 -> -630 | E23: =-'Balance Sheet'!F42 -> -928 | F23: =-'Balance Sheet'!G42 -> -823 | G23: =-'Balance Sheet'!H42 -> -823
B24: EBT | C24: =SUM(C22,C23) -> 7585 | D24: =SUM(D22,D23) -> 11527 | E24: =SUM(E22,E23) -> 9897 | F24: =SUM(F22,F23) -> 12327 | G24: =SUM(G22,G23) -> 14674
B25: Taxes | C25: =-C24*C46 -> -1592.85 | D25: =-D24*D46 -> -2420.67 | E25: =-E24*E46 -> -2078.37 | F25: =-F24*F46 -> -2588.67 | G25: =-G24*G46 -> -3081.54
B26: Net Income | C26: =C24+C25 -> 5992.15 | D26: =D24 + D25 -> 9106.33 | E26: =E24 + E25 -> 7818.63 | F26: =F24 + F25 -> 9738.33 | G26: =G24 + G25 -> 11592.46
B28: Net Income as % of Revenue | C28: =C26/C7 -> 0.25230105 | D28: =D26/D7 -> 3.8342442 | E28: =E26/E7 -> 0.25323498 | F28: =F26/F7 -> 0.25627184 | G28: =G26/G7 -> 0.24405179
B30: Assumptions:
B31: Revenue
B32: Cups Sold | C32: 5000 | D32: ='Income Statement'!C21 -> 500 | E32: 6500 | F32: 8000 | G32: 10000
B33: Average Price per Cup | C33: 5 | D33: 5 | E33: 5 | F33: 5 | G33: 5
B34: =B6&" as a % of revenue" -> Discounts as a % of revenue | C34: 0.05 | D34: 0.05 | E34: 0.05 | F34: 0.05 | G34: 0.05
B36: Cost of Goods Sold (COGS)
B37: =B9&" as a % of revenue" -> Raw Materials as a % of revenue | C37: 0.3 | D37: 0.3 | E37: 0.3 | F37: 0.3 | G37: 0.3
B38: =B10&" as a % of revenue" -> Fulfillment as a % of revenue | C38: 0.07 | D38: 0.07 | E38: 0.07 | F38: 0.07 | G38: 0.07
B39: =B11&" as a % of revenue" -> Transaction Fees as a % of revenue | C39: 0.02 | D39: 0.02 | E39: 0.02 | F39: 0.02 | G39: 0.02
B41: Operating Expenses
B42: =B16&" as a % of revenue" -> Labor as a % of revenue | C42: 0.15 | D42: 0.15 | E42: 0.15 | F42: 0.15 | G42: 0.15
B43: =B17&" as a % of revenue" -> Marketing as a % of revenue | C43: 0.05 | D43: 0.05 | E43: 0.05 | F43: 0.05 | G43: 0.05
B44: =B18&" as a % of revenue" -> SGA & Other as a % of revenue | C44: 0.05 | D44: 0.05 | E44: 0.05 | F44: 0.05 | G44: 0.05
B46: Corporate Tax Rate | C46: 0.21 | D46: 0.21 | E46: 0.21 | F46: 0.21 | G46: 0.21

Sheet Balance Sheet
B2: Balance Sheet | C2: Historical
B3: $ in actual figures | C3: 44561 | D3: 44926 | E3: 45291 | F3: 45657 | G3: 46022 | H3: 46387
B4: Current Assets
B5: Cash | C5: 5000 | D5: =C5+'Statement of Cashflows'!C18 -> -2871.8277 | E5: =D5+'Statement of Cashflows'!D18 -> 3919.2895 | F5: =E5+'Statement of Cashflows'!E18 -> 16463.524 | G5: 20901 | H5: 32423
B6: Accounts Receivable | C6: 150 | D6: =D34*D32 -> 237.5 | E6: =E34*E32 -> 261.25 | F6: =F34*F32 -> 308.75 | G6: =G34*G32 -> 380 | H6: =H34*H32 -> 475
B7: Total Current Assets | C7: =C5 +C6 -> 5150 | D7: =D5 +D6 -> -2634.3277 | E7: =E5 +E6 -> 4180.5395 | F7: 16773 | G7: =G5 +G6 -> 21281 | H7: =H5 +H6 -> 32898
B8: Non Current Assets
B9: Fixed Assets | C9: 10000 | D9: 24000 | E9: 24000 | F9: ='Balance Sheet'!E9 +'Fixed Assets'!F8 -> 24000 | G9: 29000 | H9: ='Balance Sheet'!G9 +'Fixed Assets'!H8 -> 29000
B10: Accumulated Depreciation | C10: -2000 | D10: -6952 | E10: -11905 | F10: -16857 | G10: -21810 | H10: -24762
B11: Net Fixed Assets | C11: =C9 + C10 -> 8000 | D11: =D9 + D10 -> 17048 | E11: =E9 + E10 -> 12095 | F11: =F9 + F10 -> 7143 | G11: =G9 + G10 -> 7190 | H11: =H9 + H10 -> 4238
B12: Total Non Current Assets | C12: =C11 -> 8000 | D12: =D11 -> 17048 | E12: =E11 -> 12095 | F12: =F11 -> 7143 | G12: =G11 -> 7190 | H12: =H11 -> 4238
B13: Total Assets | C13: =C7 + C12 -> 13150 | D13: 14413 | E13: =E7 + E12 -> 16275.54 | F13: =F7 + F12 -> 23916 | G13: 28472 | H13: =H7 + H12 -> 37136
B15: Current Liabilities
B16: Accounts Payable | C16: 200 | D16: =D35*D33 -> 220.33898 | E16: =E35*E33 -> 242.37288 | F16: =F35*F33 -> 286.44068 | G16: =G35*G33 -> 352.54237 | H16: =H35*H33 -> 440.67797
B17: Deferred Revenue | C17: 100 | D17: =D36*D32 -> 158.33333 | E17: =E36*E32 -> 174.16667 | F17: =F36*F32 -> 205.83333 | G17: =G36*G32 -> 253.33333 | H17: =H36*H32 -> 316.66667
B18: Total Current Liabilitites | C18: =C16+C17 -> 300 | D18: =D16+D17 -> 378.67232 | E18: =E16+E17 -> 416.53955 | F18: =F16+F17 -> 492.27401 | G18: =G16+G17 -> 605.87571 | H18: =H16+H17 -> 757.34463
B19: Non Current Liabilities
B20: Debt | C20: 10000 | D20: =C20 + D39-D40 -> 9500 | E20: =D20 + E39-E40 -> 9000 | F20: =E20 + F39-F40 -> 13250 | G20: =F20 + G39-G40 -> 12500 | H20: =G20 + H39-H40 -> 11750
B21: Total Non Current Liabilitites | C21: =C20 -> 10000 | D21: =D20 -> 9500 | E21: =E20 -> 9000 | F21: =F20 -> 13250 | G21: =G20 -> 12500 | H21: =H20 -> 11750
B22: Total Liabilitites | C22: =C18+C21 -> 10300 | D22: =D18+D21 -> 9878.6723 | E22: =E18+E21 -> 9416.5395 | F22: =F18+F21 -> 13742.274 | G22: =G18+G21 -> 13105.876 | H22: =H18+H21 -> 12507.345
B23: Equity
B24: Common Stock | C24: 300 | D24: =C24 -> 300 | E24: =D24 -> 300 | F24: =E24 -> 300 | G24: =F24 -> 300 | H24: =G24 -> 300
B25: Retained Earnings | C25: 2550 | D25: 4235 | E25: 6559 | F25: 9874 | G25: 15066 | H25: 24329
B26: Total Equity | C26: =C24+C25 -> 2850 | D26: =D24+D25 -> 4535 | E26: =E24+E25 -> 6859 | F26: =F24+F25 -> 10174 | G26: =G24+G25 -> 15366 | H26: =H24+H25 -> 24629
B27: Total Liabilities & Equity | C27: =C22 + C26 -> 13150 | D27: 14413 | E27: =E22 + E26 -> 16275.54 | F27: =F22 + F26 -> 23916.274 | G27: =G22 + G26 -> 28471.876 | H27: =H22 + H26 -> 37136.345
B29: Balance Check | C29: =C13-C27 -> 0 | D29: =D13-D27 -> 0 | E29: =E13-E27 -> 0 | F29: =F13-F27 -> -0.2740113 | G29: =G13-G27 -> 0.12429379 | H29: =H13-H27 -> -0.34463277
B31: Assumptions:
B32: Net Revenue | C32: 15000 | D32: 23750 | E32: 26125 | F32: 30875 | G32: 38000 | H32: 47500
B33: COGS | C33: 8850 | D33: =-'Income Statement'!C12 -> 9750 | E33: 10725 | F33: =-'Income Statement'!E12 -> 12675 | G33: =-'Income Statement'!F12 -> 15600 | H33: =-'Income Statement'!G12 -> 19500
B34: =B6&" as a % of revenue" -> Accounts Receivable as a % of revenue | C34: =C6/C32 -> 0.01 | D34: =C34 -> 0.01 | E34: =D34 -> 0.01 | F34: =E34 -> 0.01 | G34: =F34 -> 0.01 | H34: =G34 -> 0.01
B35: =B16&" as a % of COGS" -> Accounts Payable as a % of COGS | C35: =C16/C33 -> 0.02259887 | D35: =C35 -> 0.02259887 | E35: =D35 -> 0.02259887 | F35: =E35 -> 0.02259887 | G35: =F35 -> 0.02259887 | H35: =G35 -> 0.02259887
B36: =B17&" as a % of revenue" -> Deferred Revenue as a % of revenue | C36: =C17/C32 -> 0.0066666667 | D36: =C36 -> 0.0066666667 | E36: =D36 -> 0.0066666667 | F36: =E36 -> 0.0066666667 | G36: =F36 -> 0.0066666667 | H36: =G36 -> 0.0066666667
B38: Debt
B39: Net Borrowing | F39: 5000
B40: Debt Repayment | D40: 500 | E40: 500 | F40: 750 | G40: 750 | H40: 750
B41: Interest Rate | D41: 7 | E41: 7 | F41: 7 | G41: 7 | H41: 7
B42: Interest Payment | D42: 665 | E42: 630 | F42: 928 | G42: 823 | H42: 823

Sheet Statement of Cashflows
B2: Statement of Cashflows
B3: $ in actual figures | C3: 44562 | D3: =EDATE(C3,12) -> 44927 | E3: =EDATE(D3,12) -> 45292 | F3: =EDATE(E3,12) -> 45658 | G3: =EDATE(F3,12) -> 46023
B4: Net Income | C4: 1685 | D4: 2325 | E4: 3314 | F4: 5192 | G4: 9263
B5: Operating Activities
B6: Depreciation | C6: 4952 | D6: 4952 | E6: 4952 | F6: 4952 | G6: 2952
B7: ="Change in "&'Balance Sheet'!B6 -> Change in Accounts Receivable | C7: =-('Balance Sheet'!D6-'Balance Sheet'!C6) -> -87.5 | D7: =-('Balance Sheet'!E6-'Balance Sheet'!D6) -> -23.75 | E7: =-('Balance Sheet'!F6-'Balance Sheet'!E6) -> -47.5 | F7: =-('Balance Sheet'!G6-'Balance Sheet'!F6) -> -71.25 | G7: =-('Balance Sheet'!H6-'Balance Sheet'!G6) -> -95
B8: ="Change in "&'Balance Sheet'!B16 -> Change in Accounts Payable | C8: ='Balance Sheet'!D16-'Balance Sheet'!C16 -> 20.338983 | D8: ='Balance Sheet'!E16-'Balance Sheet'!D16 -> 22.033898 | E8: ='Balance Sheet'!F16-'Balance Sheet'!E16 -> 44.067797 | F8: ='Balance Sheet'!G16-'Balance Sheet'!F16 -> 66.101695 | G8: ='Balance Sheet'!H16-'Balance Sheet'!G16 -> 88.135593
B9: ="Change in "&'Balance Sheet'!B17 -> Change in Deferred Revenue | C9: ='Balance Sheet'!D17-'Balance Sheet'!C17 -> 58.333333 | D9: ='Balance Sheet'!E17-'Balance Sheet'!D17 -> 15.833333 | E9: ='Balance Sheet'!F17-'Balance Sheet'!E17 -> 31.666667 | F9: ='Balance Sheet'!G17-'Balance Sheet'!F17 -> 47.5 | G9: ='Balance Sheet'!H17-'Balance Sheet'!G17 -> 63.333333
B10: Operating Cash Flow | C10: =SUM(C6,C7,C8,C9) -> 4943.1723 | D10: =SUM(D6,D7,D8,D9) -> 4966.1172 | E10: =SUM(E6,E7,E8,E9) -> 4980.2345 | F10: =SUM(F6,F7,F8,F9) -> 4994.3517 | G10: =SUM(G6,G7,G8,G9) -> 3008.4689
B11: Investing Activities
B12: CapEx | C12: -14000 | D12: =-'Fixed Assets'!E8 -> 0 | E12: =-'Fixed Assets'!F8 -> 0 | F12: -5000 | G12: =-'Fixed Assets'!H8 -> 0
B13: Investing Cash Flow | C13: =C12 -> -14000 | D13: =D12 -> 0 | E13: =E12 -> 0 | F13: =F12 -> -5000 | G13: =G12 -> 0
B14: Financing Activities
B15: Debt Repayment | C15: =-'Balance Sheet'!D40 -> -500 | D15: =-'Balance Sheet'!E40 -> -500 | E15: =-'Balance Sheet'!F40 -> -750 | F15: =-'Balance Sheet'!G40 -> -750 | G15: =-'Balance Sheet'!H40 -> -750
B16: Net Borrowings | C16: ='Balance Sheet'!D39 -> 0 | D16: ='Balance Sheet'!E39 -> 0 | E16: ='Balance Sheet'!F39 -> 5000 | F16: ='Balance Sheet'!G39 -> 0 | G16: ='Balance Sheet'!H39 -> 0
B17: Financing Cash Flow | C17: =C15 -> -500 | D17: =D15 -> -500 | E17: =E15+E16 -> 4250 | F17: =F15 -> -750 | G17: =G15 -> -750
B18: Net Cash Flow | C18: =C4+C10+C13+C17 -> -7871.8277 | D18: =D4+D10+D13+D17 -> 6791.1172 | E18: =E4+E10+E13+E17 -> 12544.234 | F18: =F4+F10+F13+F17 -> 4436.3517 | G18: =G4+G10+G13+G17 -> 11521.469

Sheet Fixed Assets
B2: Fixed Assets
B3: $ in actual figures | C3: Asset Life (Years) | D3: 44926 | E3: =EDATE(D3,12) -> 45291 | F3: =EDATE(E3,12) -> 45657 | G3: =EDATE(F3,12) -> 46022 | H3: =EDATE(G3,12) -> 46387
B4: CapEx | C4: 1685
B5: Lemon Crusher | C5: 3 | D5: 3 | E5: 3 | F5: 3 | G5: 3
B6: Ice Machine | C6: 7 | D6: 7 | E6: 7 | F6: 7 | G6: 7
B7: Refrigerator | C7: 7 | D7: 7 | E7: 7 | F7: 7 | G7: 7
B8: Total CapEx | H8: =SUM(H5:H7) -> 0
B10: Depreciation
B11: Existing Equipment
B12: =B5 -> Lemon Crusher | C12: =-'Fixed Assets'!D8 -> 0 | D12: =-'Fixed Assets'!E8 -> 0 | E12: =-'Fixed Assets'!F8 -> 0 | F12: =-'Fixed Assets'!G8 -> 0 | G12: =-'Fixed Assets'!H8 -> 0 | H12: =G5/C5 -> 1
B13: =B6 -> Ice Machine | C13: =C12 -> 0 | D13: =D12 -> 0 | E13: =E12 -> 0 | F13: =F12 -> 0 | G13: =G12 -> 0 | H13: =D6/C6 -> 1
B14: =B7 -> Refrigerator | H14: =D7/C7 -> 1
B15: Total D&A | C15: =-'Balance Sheet'!D40 -> -500 | D15: =-'Balance Sheet'!E40 -> -500 | E15: =-'Balance Sheet'!F40 -> -750 | F15: =-'Balance Sheet'!G40 -> -750 | G15: =-'Balance Sheet'!H40 -> -750 | H15: =SUM(H11:H14) -> 3
C16: ='Balance Sheet'!D39 -> 0 | D16: ='Balance Sheet'!E39 -> 0 | E16: ='Balance Sheet'!F39 -> 5000 | F16: ='Balance Sheet'!G39 -> 0 | G16: ='Balance Sheet'!H39 -> 0
C17: =C15 -> -500 | D17: =D15 -> -500 | E17: =E15 -> -750 | F17: =F15 -> -750 | G17: =G15 -> -750
C18: =C4+C10+C13+C17 -> 1185 | D18: =D4+D10+D13+D17 -> -500 | E18: =E4+E10+E13+E17 -> -750 | F18: =F4+F10+F13+F17 -> -750 | G18: =G4+G10+G13+G17 -> -750
